weather_cli/__init__.py
weather_cli/weather.py
weather_cli_open_weather-1.0.1.dist-info/licenses/LICENSE.txt
weather_cli_open_weather-1.0.1.dist-info/METADATA
weather_cli_open_weather-1.0.1.dist-info/WHEEL
weather_cli_open_weather-1.0.1.dist-info/entry_points.txt
weather_cli_open_weather-1.0.1.dist-info/top_level.txt
weather_cli_open_weather-1.0.1.dist-info/RECORD
